{
    "estimates":{
        "totalRevenues":"2,129,430",
        "totalTransactions":"1,520",
        "totalLikes":"9,721",
        "totalUsers":"892"
    },
    "activites":[{
        "user":[
            [100,430,140,450,160,260],
            [100,430,240,180,360,260],
            [100,345,195,100,190,260]
        ]
    },
    {
    "guest":[
        [200,395,205,295,195,430],
        [200,300,200,255,185,430],
        [200,355,265,430,195,430]
    ]
    }
],
"products":[
    {
        "product":["Super Hoodies","Custom Short Pants","Basic Tees"],
         "percentages":[14,31,55]
    },      
    {
     "product": ["Super Sneakers"," Long Pants","Checked Shirts"],
    "percentages": [50,20,30]
    }, {
   "product":"Track Pants","Sunglasses","Sweatshirts",
    "percentages":[25,30,45]
    }
],
      

    "schedules":[
        {
            "title":"Meeting suppliers from Kuta Bali",
            "time":"14:00-15:00",
            "place":"at Sunset road,Kuta,Bali"
        },       
         {
            "title":"Check operation at Giga Factory 1",
            "time":"18:00-20:00",
            "place":"at Central Jakarta"
        }

    ]
}
    
